nanohttp/__init__.py
nanohttp/application.py
nanohttp/configuration.py
nanohttp/constants.py
nanohttp/contexts.py
nanohttp/controllers.py
nanohttp/decorators.py
nanohttp/exceptions.py
nanohttp/helpers.py
nanohttp/validation.py
nanohttp/cli/__init__.py
nanohttp/cli/entry.py
nanohttp/cli/parser.py
nanohttp/cli/tests/__init__.py
nanohttp/cli/tests/conftest.py
nanohttp/cli/tests/test_cli.py
nanohttp/tests/__init__.py
nanohttp/tests/conftest.py
nanohttp/tests/helpers.py
nanohttp/tests/test_action_decorator.py
nanohttp/tests/test_application_hooks.py
nanohttp/tests/test_chunked_streaming.py
nanohttp/tests/test_cookies.py
nanohttp/tests/test_exception_classes.py
nanohttp/tests/test_exceptions.py
nanohttp/tests/test_forms.py
nanohttp/tests/test_int_or_notfound.py
nanohttp/tests/test_lazyattribute.py
nanohttp/tests/test_object_dispatcher.py
nanohttp/tests/test_pileline.py
nanohttp/tests/test_querystring.py
nanohttp/tests/test_quickstart.py
nanohttp/tests/test_regex_route_controller.py
nanohttp/tests/test_rest_controller.py
nanohttp/tests/test_static_controller.py
nanohttp/tests/test_url_parameters.py
nanohttp/tests/test_validation.py
nanohttp-1.11.7.dist-info/LICENSE
nanohttp-1.11.7.dist-info/METADATA
nanohttp-1.11.7.dist-info/WHEEL
nanohttp-1.11.7.dist-info/entry_points.txt
nanohttp-1.11.7.dist-info/top_level.txt
nanohttp-1.11.7.dist-info/RECORD
